howl/__init__.py
howl/admin.py
howl/apps.py
howl/models.py
howl/operators.py
howl/signals.py
howl/conf/__init__.py
howl/conf/settings.py
howl/locale/de/LC_MESSAGES/django.mo
howl/locale/de/LC_MESSAGES/django.po
howl/migrations/0001_initial.py
howl/migrations/0002_auto_20151205_2110.py
howl/migrations/0003_alert_value.py
howl/migrations/0004_auto_20160210_0811.py
howl/migrations/0005_auto_20160210_2042.py
howl/migrations/0006_auto_20160409_1102.py
howl/migrations/0007_auto_20160409_1127.py
howl/migrations/0008_auto_20170101_0830.py
howl/migrations/0009_auto_20181208_0351.py
howl/migrations/__init__.py
django_howl-1.1.0.dist-info/LICENSE.rst
django_howl-1.1.0.dist-info/METADATA
django_howl-1.1.0.dist-info/WHEEL
django_howl-1.1.0.dist-info/top_level.txt
django_howl-1.1.0.dist-info/RECORD
