Metadata-Version: 2.1
Name: django-howl
Version: 1.1.0
Summary: Django app to observe almost everything you want and pushes notifications to signals.
Home-page: https://github.com/deluge/django-howl
Author: Benjamin Banduhn, Stephan Jaekel
Author-email: deluge@banduhn.com
License: UNKNOWN
Project-URL: Bug Reports, https://github.com/deluge/django-howl/issues
Project-URL: Source, https://github.com/deluge/django-howl
Keywords: django howl observer watchdog alert signal
Platform: UNKNOWN
Classifier: Development Status :: 5 - Production/Stable
Classifier: Environment :: Web Environment
Classifier: Framework :: Django
Classifier: Intended Audience :: Developers
Classifier: License :: OSI Approved :: BSD License
Classifier: Programming Language :: Python :: 3
Classifier: Programming Language :: Python :: 3.6
Classifier: Programming Language :: Python :: 3.7
Classifier: Programming Language :: Python :: 3.8
Classifier: Programming Language :: Python :: 3.9
Requires-Dist: Django (<3.3,>=2.2)
Provides-Extra: dev
Requires-Dist: coverage[toml] (>=5.3) ; extra == 'dev'
Requires-Dist: factory-boy (>=3.1.0) ; extra == 'dev'
Requires-Dist: freezegun (>=1.0.0) ; extra == 'dev'
Requires-Dist: pytest (>=6.1.1) ; extra == 'dev'
Requires-Dist: pytest-black (>=0.3.12) ; extra == 'dev'
Requires-Dist: pytest-cov (>=2.10.1) ; extra == 'dev'
Requires-Dist: pytest-django (>=3.10.0) ; extra == 'dev'
Requires-Dist: pytest-flake8 (>=1.0.6) ; extra == 'dev'
Requires-Dist: pytest-isort (>=1.2.0) ; extra == 'dev'
Requires-Dist: sphinx (>=3.2.1) ; extra == 'dev'
Requires-Dist: sphinx-rtd-theme (==0.5.0) ; extra == 'dev'
Requires-Dist: vcrpy (>=4.1.1) ; extra == 'dev'
